[{"_id":"5ec4a0958b6aca48aa9f1c63","date":1589944468998,"sgv":428,"delta":0,"sysTime":"2020-05-20T03:14:29.637Z","device":"Tomato","direction":"FortyFiveDown","dateString":"2020-05-20T03:14:29.637Z","type":"sgv","utcOffset":0},{"_id":"5ec4a0958b6aca48aa9f1c65","date":1589944163873,"sgv":432,"delta":0,"sysTime":"2020-05-20T03:14:29.644Z","device":"Tomato","direction":"FortyFiveDown","dateString":"2020-05-20T03:14:29.644Z","type":"sgv","utcOffset":0},{"_id":"5ec49e3e8b6aca48aa9f02b4","date":1589943869760,"sgv":428,"delta":0,"sysTime":"2020-05-20T03:04:30.842Z","device":"Tomato","direction":"Flat","dateString":"2020-05-20T03:04:30.842Z","type":"sgv","utcOffset":0},{"_id":"5ec49e3e8b6aca48aa9f02b5","date":1589943812471,"sgv":429,"delta":0,"sysTime":"2020-05-20T03:04:30.849Z","device":"Tomato","direction":"Flat","dateString":"2020-05-20T03:04:30.849Z","type":"sgv","utcOffset":0},{"_id":"5ec49e3e8b6aca48aa9f02b6","date":1589943512471,"sgv":427,"delta":0,"sysTime":"2020-05-20T03:04:30.855Z","device":"Tomato","direction":"Flat","dateString":"2020-05-20T03:04:30.855Z","type":"sgv","utcOffset":0},{"_id":"5ec49be68b6aca48aa9ee960","date":1589943269817,"sgv":428,"delta":0,"sysTime":"2020-05-20T02:54:30.513Z","device":"Tomato","direction":"Flat","dateString":"2020-05-20T02:54:30.513Z","type":"sgv","utcOffset":0},{"_id":"5ec49be68b6aca48aa9ee962","date":1589943204366,"sgv":429,"delta":0,"sysTime":"2020-05-20T02:54:30.520Z","device":"Tomato","direction":"Flat","dateString":"2020-05-20T02:54:30.520Z","type":"sgv","utcOffset":0},{"_id":"5ec49ab38b6aca48aa9edc6b","date":1589942962104,"sgv":411,"delta":0,"sysTime":"2020-05-20T02:49:23.072Z","device":"Tomato","direction":"Flat","dateString":"2020-05-20T02:49:23.072Z","type":"sgv","utcOffset":0},{"_id":"5ec499858b6aca48aa9ecf95","date":1589942661324,"sgv":421,"delta":0,"sysTime":"2020-05-20T02:44:21.656Z","device":"Tomato","direction":"FortyFiveUp","dateString":"2020-05-20T02:44:21.656Z","type":"sgv","utcOffset":0},{"_id":"5ec499858b6aca48aa9ecf97","date":1589942600394,"sgv":421,"delta":0,"sysTime":"2020-05-20T02:44:21.663Z","device":"Tomato","direction":"FortyFiveUp","dateString":"2020-05-20T02:44:21.663Z","type":"sgv","utcOffset":0},{"_id":"5ec4972d8b6aca48aa9eb602","date":1589942061260,"sgv":401,"delta":1,"sysTime":"2020-05-20T02:34:21.587Z","device":"Tomato","direction":"FortyFiveUp","dateString":"2020-05-20T02:34:21.587Z","type":"sgv","utcOffset":0},{"_id":"5ec4972d8b6aca48aa9eb603","date":1589942004257,"sgv":400,"delta":1,"sysTime":"2020-05-20T02:34:21.594Z","device":"Tomato","direction":"FortyFiveUp","dateString":"2020-05-20T02:34:21.594Z","type":"sgv","utcOffset":0},{"_id":"5ec496028b6aca48aa9ea91c","date":1589941761351,"sgv":393,"delta":1,"sysTime":"2020-05-20T02:29:21.967Z","device":"Tomato","direction":"FortyFiveUp","dateString":"2020-05-20T02:29:21.967Z","type":"sgv","utcOffset":0},{"_id":"5ec496028b6aca48aa9ea91d","date":1589941704275,"sgv":393,"delta":1,"sysTime":"2020-05-20T02:29:21.976Z","device":"Tomato","direction":"FortyFiveUp","dateString":"2020-05-20T02:29:21.976Z","type":"sgv","utcOffset":0},{"_id":"5ec494d68b6aca48aa9e9c4d","date":1589941461317,"sgv":381,"delta":1,"sysTime":"2020-05-20T02:24:21.940Z","device":"Tomato","direction":"FortyFiveUp","dateString":"2020-05-20T02:24:21.940Z","type":"sgv","utcOffset":0},{"_id":"5ec493a98b6aca48aa9e8e96","date":1589941161277,"sgv":369,"delta":0,"sysTime":"2020-05-20T02:19:21.629Z","device":"Tomato","direction":"FortyFiveUp","dateString":"2020-05-20T02:19:21.629Z","type":"sgv","utcOffset":0},{"_id":"5ec4927d8b6aca48aa9e7df2","date":1589940861142,"sgv":365,"delta":1,"sysTime":"2020-05-20T02:14:21.515Z","device":"Tomato","direction":"FortyFiveUp","dateString":"2020-05-20T02:14:21.515Z","type":"sgv","utcOffset":0},{"_id":"5ec4927d8b6aca48aa9e7df3","date":1589940800186,"sgv":364,"delta":1,"sysTime":"2020-05-20T02:14:21.522Z","device":"Tomato","direction":"FortyFiveUp","dateString":"2020-05-20T02:14:21.522Z","type":"sgv","utcOffset":0},{"_id":"5ec490268b6aca48aa9e64b5","date":1589940261766,"sgv":333,"delta":1,"sysTime":"2020-05-20T02:04:22.375Z","device":"Tomato","direction":"FortyFiveUp","dateString":"2020-05-20T02:04:22.375Z","type":"sgv","utcOffset":0},{"_id":"5ec48efa8b6aca48aa9e57a4","date":1589939961250,"sgv":325,"delta":1,"sysTime":"2020-05-20T01:59:21.864Z","device":"Tomato","direction":"FortyFiveUp","dateString":"2020-05-20T01:59:21.864Z","type":"sgv","utcOffset":0},{"_id":"5ec48efa8b6aca48aa9e57a5","date":1589939900274,"sgv":325,"delta":1,"sysTime":"2020-05-20T01:59:21.871Z","device":"Tomato","direction":"FortyFiveUp","dateString":"2020-05-20T01:59:21.871Z","type":"sgv","utcOffset":0},{"_id":"5ec48ca38b6aca48aa9e3ddd","date":1589939362716,"sgv":291,"delta":2,"sysTime":"2020-05-20T01:49:23.336Z","device":"Tomato","direction":"FortyFiveUp","dateString":"2020-05-20T01:49:23.336Z","type":"sgv","utcOffset":0},{"_id":"5ec48ca38b6aca48aa9e3dde","date":1589939296214,"sgv":289,"delta":2,"sysTime":"2020-05-20T01:49:23.342Z","device":"Tomato","direction":"FortyFiveUp","dateString":"2020-05-20T01:49:23.342Z","type":"sgv","utcOffset":0},{"_id":"5ec48a498b6aca48aa9e2437","date":1589938761311,"sgv":257,"delta":1,"sysTime":"2020-05-20T01:39:21.651Z","device":"Tomato","direction":"FortyFiveUp","dateString":"2020-05-20T01:39:21.651Z","type":"sgv","utcOffset":0},{"_id":"5ec48a498b6aca48aa9e2438","date":1589938704154,"sgv":257,"delta":1,"sysTime":"2020-05-20T01:39:21.658Z","device":"Tomato","direction":"FortyFiveUp","dateString":"2020-05-20T01:39:21.658Z","type":"sgv","utcOffset":0},{"_id":"5ec4891e8b6aca48aa9e1557","date":1589938461603,"sgv":239,"delta":1,"sysTime":"2020-05-20T01:34:22.208Z","device":"Tomato","direction":"FortyFiveUp","dateString":"2020-05-20T01:34:22.208Z","type":"sgv","utcOffset":0},{"_id":"5ec4891e8b6aca48aa9e1558","date":1589938404242,"sgv":238,"delta":1,"sysTime":"2020-05-20T01:34:22.214Z","device":"Tomato","direction":"FortyFiveUp","dateString":"2020-05-20T01:34:22.214Z","type":"sgv","utcOffset":0},{"_id":"5ec487f38b6aca48aa9e0871","date":1589938162251,"sgv":218,"delta":2,"sysTime":"2020-05-20T01:29:22.932Z","device":"Tomato","direction":"FortyFiveUp","dateString":"2020-05-20T01:29:22.932Z","type":"sgv","utcOffset":0},{"_id":"5ec486c58b6aca48aa9dfb9a","date":1589937861424,"sgv":193,"delta":1,"sysTime":"2020-05-20T01:24:21.761Z","device":"Tomato","direction":"FortyFiveUp","dateString":"2020-05-20T01:24:21.761Z","type":"sgv","utcOffset":0},{"_id":"5ec4859a8b6aca48aa9deeb7","date":1589937561693,"sgv":178,"delta":1,"sysTime":"2020-05-20T01:19:22.288Z","device":"Tomato","direction":"FortyFiveUp","dateString":"2020-05-20T01:19:22.288Z","type":"sgv","utcOffset":0},{"_id":"5ec4846e8b6aca48aa9de1df","date":1589937261553,"sgv":146,"delta":2,"sysTime":"2020-05-20T01:14:21.892Z","device":"Tomato","direction":"FortyFiveUp","dateString":"2020-05-20T01:14:21.892Z","type":"sgv","utcOffset":0},{"_id":"5ec4846e8b6aca48aa9de1e1","date":1589937200561,"sgv":144,"delta":2,"sysTime":"2020-05-20T01:14:21.899Z","device":"Tomato","direction":"FortyFiveUp","dateString":"2020-05-20T01:14:21.899Z","type":"sgv","utcOffset":0},{"_id":"5ec483388b6aca48aa9dd47c","date":1589936952099,"sgv":120,"delta":0,"sysTime":"2020-05-20T01:09:12.448Z","device":"Tomato","direction":"Flat","dateString":"2020-05-20T01:09:12.448Z","type":"sgv","utcOffset":0},{"_id":"5ec483388b6aca48aa9dd47d","date":1589936891144,"sgv":120,"delta":0,"sysTime":"2020-05-20T01:09:12.454Z","device":"Tomato","direction":"Flat","dateString":"2020-05-20T01:09:12.454Z","type":"sgv","utcOffset":0},{"_id":"5ec482088b6aca48aa9dc767","date":1589936647757,"sgv":107,"delta":0,"sysTime":"2020-05-20T01:04:08.315Z","device":"Tomato","direction":"Flat","dateString":"2020-05-20T01:04:08.315Z","type":"sgv","utcOffset":0},{"_id":"5ec480d98b6aca48aa9dba32","date":1589936344751,"sgv":102,"delta":0,"sysTime":"2020-05-20T00:59:05.310Z","device":"Tomato","direction":"Flat","dateString":"2020-05-20T00:59:05.310Z","type":"sgv","utcOffset":0},{"_id":"5ec480d98b6aca48aa9dba33","date":1589936287409,"sgv":101,"delta":0,"sysTime":"2020-05-20T00:59:05.317Z","device":"Tomato","direction":"Flat","dateString":"2020-05-20T00:59:05.317Z","type":"sgv","utcOffset":0},{"_id":"5ec47fad8b6aca48aa9dad4f","date":1589936044223,"sgv":95,"delta":0,"sysTime":"2020-05-20T00:54:04.939Z","device":"Tomato","direction":"Flat","dateString":"2020-05-20T00:54:04.939Z","type":"sgv","utcOffset":0},{"_id":"5ec47e818b6aca48aa9da055","date":1589935744701,"sgv":102,"delta":0,"sysTime":"2020-05-20T00:49:05.461Z","device":"Tomato","direction":"FortyFiveUp","dateString":"2020-05-20T00:49:05.461Z","type":"sgv","utcOffset":0},{"_id":"5ec47e818b6aca48aa9da058","date":1589935687564,"sgv":102,"delta":0,"sysTime":"2020-05-20T00:49:05.469Z","device":"Tomato","direction":"FortyFiveUp","dateString":"2020-05-20T00:49:05.469Z","type":"sgv","utcOffset":0},{"_id":"5ec47d568b6aca48aa9d9394","date":1589935444985,"sgv":89,"delta":1,"sysTime":"2020-05-20T00:44:06.045Z","device":"Tomato","direction":"FortyFiveUp","dateString":"2020-05-20T00:44:06.045Z","type":"sgv","utcOffset":0},{"_id":"5ec47c288b6aca48aa9d8691","date":1589935144436,"sgv":70,"delta":0,"sysTime":"2020-05-20T00:39:04.728Z","device":"Tomato","direction":"Flat","dateString":"2020-05-20T00:39:04.728Z","type":"sgv","utcOffset":0},{"_id":"5ec47c288b6aca48aa9d8693","date":1589935087058,"sgv":70,"delta":0,"sysTime":"2020-05-20T00:39:04.735Z","device":"Tomato","direction":"Flat","dateString":"2020-05-20T00:39:04.735Z","type":"sgv","utcOffset":0},{"_id":"5ec47afd8b6aca48aa9d796b","date":1589934844574,"sgv":70,"delta":0,"sysTime":"2020-05-20T00:34:05.134Z","device":"Tomato","direction":"Flat","dateString":"2020-05-20T00:34:05.134Z","type":"sgv","utcOffset":0},{"_id":"5ec47afd8b6aca48aa9d796c","date":1589934787243,"sgv":70,"delta":0,"sysTime":"2020-05-20T00:34:05.141Z","device":"Tomato","direction":"Flat","dateString":"2020-05-20T00:34:05.141Z","type":"sgv","utcOffset":0},{"_id":"5ec47afd8b6aca48aa9d796d","date":1589934487243,"sgv":69,"delta":0,"sysTime":"2020-05-20T00:34:05.147Z","device":"Tomato","direction":"Flat","dateString":"2020-05-20T00:34:05.147Z","type":"sgv","utcOffset":0},{"_id":"5ec478a48b6aca48aa9d5e27","date":1589934244190,"sgv":65,"delta":0,"sysTime":"2020-05-20T00:24:04.509Z","device":"Tomato","direction":"Flat","dateString":"2020-05-20T00:24:04.509Z","type":"sgv","utcOffset":0},{"_id":"5ec478a48b6aca48aa9d5e28","date":1589934183199,"sgv":65,"delta":0,"sysTime":"2020-05-20T00:24:04.519Z","device":"Tomato","direction":"Flat","dateString":"2020-05-20T00:24:04.519Z","type":"sgv","utcOffset":0},{"_id":"5ec478a48b6aca48aa9d5e29","date":1589933883199,"sgv":65,"delta":0,"sysTime":"2020-05-20T00:24:04.527Z","device":"Tomato","direction":"Flat","dateString":"2020-05-20T00:24:04.527Z","type":"sgv","utcOffset":0},{"_id":"5ec476448b6aca48aa9d42d8","date":1589933635721,"sgv":63,"delta":0,"sysTime":"2020-05-20T00:13:56.020Z","device":"Tomato","direction":"Flat","dateString":"2020-05-20T00:13:56.020Z","type":"sgv","utcOffset":0},{"_id":"5ec476448b6aca48aa9d42d9","date":1589933578554,"sgv":63,"delta":0,"sysTime":"2020-05-20T00:13:56.028Z","device":"Tomato","direction":"Flat","dateString":"2020-05-20T00:13:56.028Z","type":"sgv","utcOffset":0},{"_id":"5ec475198b6aca48aa9d351d","date":1589933336100,"sgv":65,"delta":0,"sysTime":"2020-05-20T00:08:56.415Z","device":"Tomato","direction":"Flat","dateString":"2020-05-20T00:08:56.415Z","type":"sgv","utcOffset":0},{"_id":"5ec475188b6aca48aa9d3518","date":1589933278750,"sgv":65,"delta":0,"sysTime":"2020-05-20T00:08:56.422Z","device":"Tomato","direction":"Flat","dateString":"2020-05-20T00:08:56.422Z","type":"sgv","utcOffset":0},{"_id":"5ec475198b6aca48aa9d351c","date":1589932978750,"sgv":65,"delta":0,"sysTime":"2020-05-20T00:08:56.428Z","device":"Tomato","direction":"Flat","dateString":"2020-05-20T00:08:56.428Z","type":"sgv","utcOffset":0},{"_id":"5ec472c28b6aca48aa9d1847","date":1589932737669,"sgv":63,"delta":0,"sysTime":"2020-05-19T23:58:58.247Z","device":"Tomato","direction":"Flat","dateString":"2020-05-19T23:58:58.247Z","type":"sgv","utcOffset":0},{"_id":"5ec471948b6aca48aa9d09fb","date":1589932436064,"sgv":68,"delta":0,"sysTime":"2020-05-19T23:53:56.378Z","device":"Tomato","direction":"Flat","dateString":"2020-05-19T23:53:56.378Z","type":"sgv","utcOffset":0},{"_id":"5ec470688b6aca48aa9cfc84","date":1589932136134,"sgv":65,"delta":0,"sysTime":"2020-05-19T23:48:56.441Z","device":"Tomato","direction":"Flat","dateString":"2020-05-19T23:48:56.441Z","type":"sgv","utcOffset":0},{"_id":"5ec470688b6aca48aa9cfc85","date":1589932078910,"sgv":66,"delta":0,"sysTime":"2020-05-19T23:48:56.447Z","device":"Tomato","direction":"Flat","dateString":"2020-05-19T23:48:56.447Z","type":"sgv","utcOffset":0},{"_id":"5ec46f3c8b6aca48aa9cee7a","date":1589931835688,"sgv":65,"delta":0,"sysTime":"2020-05-19T23:43:56.000Z","device":"Tomato","direction":"Flat","dateString":"2020-05-19T23:43:56.000Z","type":"sgv","utcOffset":0},{"_id":"5ec46e108b6aca48aa9ce09a","date":1589931536060,"sgv":66,"delta":0,"sysTime":"2020-05-19T23:38:56.654Z","device":"Tomato","direction":"Flat","dateString":"2020-05-19T23:38:56.654Z","type":"sgv","utcOffset":0},{"_id":"5ec46ce48b6aca48aa9cd2c1","date":1589931235620,"sgv":66,"delta":0,"sysTime":"2020-05-19T23:33:55.930Z","device":"Tomato","direction":"Flat","dateString":"2020-05-19T23:33:55.930Z","type":"sgv","utcOffset":0},{"_id":"5ec46bb88b6aca48aa9cc497","date":1589930935689,"sgv":66,"delta":0,"sysTime":"2020-05-19T23:28:55.997Z","device":"Tomato","direction":"Flat","dateString":"2020-05-19T23:28:55.997Z","type":"sgv","utcOffset":0},{"_id":"5ec46a8c8b6aca48aa9cb6aa","date":1589930635652,"sgv":66,"delta":0,"sysTime":"2020-05-19T23:23:55.978Z","device":"Tomato","direction":"Flat","dateString":"2020-05-19T23:23:55.978Z","type":"sgv","utcOffset":0},{"_id":"5ec469608b6aca48aa9ca891","date":1589930335929,"sgv":68,"delta":0,"sysTime":"2020-05-19T23:18:56.236Z","device":"Tomato","direction":"Flat","dateString":"2020-05-19T23:18:56.236Z","type":"sgv","utcOffset":0},{"_id":"5ec469608b6aca48aa9ca892","date":1589930278803,"sgv":67,"delta":0,"sysTime":"2020-05-19T23:18:56.243Z","device":"Tomato","direction":"Flat","dateString":"2020-05-19T23:18:56.243Z","type":"sgv","utcOffset":0},{"_id":"5ec468348b6aca48aa9c9ad6","date":1589930035993,"sgv":68,"delta":0,"sysTime":"2020-05-19T23:13:56.305Z","device":"Tomato","direction":"Flat","dateString":"2020-05-19T23:13:56.305Z","type":"sgv","utcOffset":0},{"_id":"5ec467088b6aca48aa9c8d06","date":1589929735853,"sgv":70,"delta":0,"sysTime":"2020-05-19T23:08:56.440Z","device":"Tomato","direction":"Flat","dateString":"2020-05-19T23:08:56.440Z","type":"sgv","utcOffset":0},{"_id":"5ec467088b6aca48aa9c8d08","date":1589929670805,"sgv":70,"delta":0,"sysTime":"2020-05-19T23:08:56.447Z","device":"Tomato","direction":"Flat","dateString":"2020-05-19T23:08:56.447Z","type":"sgv","utcOffset":0},{"_id":"5ec465d28b6aca48aa9c7ec7","date":1589929426195,"sgv":70,"delta":0,"sysTime":"2020-05-19T23:03:46.790Z","device":"Tomato","direction":"Flat","dateString":"2020-05-19T23:03:46.790Z","type":"sgv","utcOffset":0},{"_id":"5ec464a68b6aca48aa9c7123","date":1589929126061,"sgv":61,"delta":0,"sysTime":"2020-05-19T22:58:46.634Z","device":"Tomato","direction":"Flat","dateString":"2020-05-19T22:58:46.634Z","type":"sgv","utcOffset":0},{"_id":"5ec464a68b6aca48aa9c7125","date":1589929068962,"sgv":61,"delta":0,"sysTime":"2020-05-19T22:58:46.641Z","device":"Tomato","direction":"Flat","dateString":"2020-05-19T22:58:46.641Z","type":"sgv","utcOffset":0},{"_id":"5ec4637a8b6aca48aa9c63a0","date":1589928826123,"sgv":61,"delta":0,"sysTime":"2020-05-19T22:53:46.707Z","device":"Tomato","direction":"Flat","dateString":"2020-05-19T22:53:46.707Z","type":"sgv","utcOffset":0},{"_id":"5ec462518b6aca48aa9c55c8","date":1589928529163,"sgv":61,"delta":0,"sysTime":"2020-05-19T22:48:49.745Z","device":"Tomato","direction":"Flat","dateString":"2020-05-19T22:48:49.745Z","type":"sgv","utcOffset":0},{"_id":"5ec461228b6aca48aa9c4800","date":1589928226164,"sgv":65,"delta":0,"sysTime":"2020-05-19T22:43:46.475Z","device":"Tomato","direction":"Flat","dateString":"2020-05-19T22:43:46.475Z","type":"sgv","utcOffset":0},{"_id":"5ec461228b6aca48aa9c47ff","date":1589928168931,"sgv":65,"delta":0,"sysTime":"2020-05-19T22:43:46.483Z","device":"Tomato","direction":"Flat","dateString":"2020-05-19T22:43:46.483Z","type":"sgv","utcOffset":0},{"_id":"5ec45ff88b6aca48aa9c3a60","date":1589927927561,"sgv":63,"delta":0,"sysTime":"2020-05-19T22:38:48.141Z","device":"Tomato","direction":"Flat","dateString":"2020-05-19T22:38:48.141Z","type":"sgv","utcOffset":0},{"_id":"5ec45ff88b6aca48aa9c3a61","date":1589927861258,"sgv":63,"delta":0,"sysTime":"2020-05-19T22:38:48.148Z","device":"Tomato","direction":"Flat","dateString":"2020-05-19T22:38:48.148Z","type":"sgv","utcOffset":0},{"_id":"5ec45d9e8b6aca48aa9c1ed5","date":1589927325856,"sgv":65,"delta":0,"sysTime":"2020-05-19T22:28:46.170Z","device":"Tomato","direction":"Flat","dateString":"2020-05-19T22:28:46.170Z","type":"sgv","utcOffset":0},{"_id":"5ec45c728b6aca48aa9c111e","date":1589927026432,"sgv":70,"delta":0,"sysTime":"2020-05-19T22:23:46.729Z","device":"Tomato","direction":"Flat","dateString":"2020-05-19T22:23:46.729Z","type":"sgv","utcOffset":0},{"_id":"5ec45b468b6aca48aa9c00d4","date":1589926725990,"sgv":70,"delta":0,"sysTime":"2020-05-19T22:18:46.597Z","device":"Tomato","direction":"Flat","dateString":"2020-05-19T22:18:46.597Z","type":"sgv","utcOffset":0},{"_id":"5ec45a1e8b6aca48aa9bf300","date":1589926429639,"sgv":72,"delta":0,"sysTime":"2020-05-19T22:13:50.304Z","device":"Tomato","direction":"Flat","dateString":"2020-05-19T22:13:50.304Z","type":"sgv","utcOffset":0},{"_id":"5ec458f08b6aca48aa9be516","date":1589926128272,"sgv":73,"delta":0,"sysTime":"2020-05-19T22:08:48.566Z","device":"Tomato","direction":"Flat","dateString":"2020-05-19T22:08:48.566Z","type":"sgv","utcOffset":0},{"_id":"5ec457c38b6aca48aa9bd780","date":1589925826301,"sgv":75,"delta":0,"sysTime":"2020-05-19T22:03:46.864Z","device":"Tomato","direction":"Flat","dateString":"2020-05-19T22:03:46.864Z","type":"sgv","utcOffset":0},{"_id":"5ec456968b6aca48aa9bc9b4","date":1589925526057,"sgv":75,"delta":0,"sysTime":"2020-05-19T21:58:46.637Z","device":"Tomato","direction":"Flat","dateString":"2020-05-19T21:58:46.637Z","type":"sgv","utcOffset":0},{"_id":"5ec4556a8b6aca48aa9bbbc5","date":1589925226122,"sgv":77,"delta":0,"sysTime":"2020-05-19T21:53:46.697Z","device":"Tomato","direction":"Flat","dateString":"2020-05-19T21:53:46.697Z","type":"sgv","utcOffset":0},{"_id":"5ec4556a8b6aca48aa9bbbc7","date":1589925168790,"sgv":77,"delta":0,"sysTime":"2020-05-19T21:53:46.704Z","device":"Tomato","direction":"Flat","dateString":"2020-05-19T21:53:46.704Z","type":"sgv","utcOffset":0},{"_id":"5ec4543f8b6aca48aa9badb4","date":1589924926702,"sgv":79,"delta":0,"sysTime":"2020-05-19T21:48:47.000Z","device":"Tomato","direction":"Flat","dateString":"2020-05-19T21:48:47.000Z","type":"sgv","utcOffset":0},{"_id":"5ec453138b6aca48aa9b9fda","date":1589924626872,"sgv":81,"delta":0,"sysTime":"2020-05-19T21:43:47.171Z","device":"Tomato","direction":"Flat","dateString":"2020-05-19T21:43:47.171Z","type":"sgv","utcOffset":0},{"_id":"5ec451e68b6aca48aa9b91a0","date":1589924326117,"sgv":86,"delta":0,"sysTime":"2020-05-19T21:38:46.424Z","device":"Tomato","direction":"Flat","dateString":"2020-05-19T21:38:46.424Z","type":"sgv","utcOffset":0},{"_id":"5ec450bb8b6aca48aa9b83c3","date":1589924026501,"sgv":81,"delta":0,"sysTime":"2020-05-19T21:33:47.074Z","device":"Tomato","direction":"Flat","dateString":"2020-05-19T21:33:47.074Z","type":"sgv","utcOffset":0},{"_id":"5ec44f8f8b6aca48aa9b75f0","date":1589923726355,"sgv":77,"delta":0,"sysTime":"2020-05-19T21:28:46.926Z","device":"Tomato","direction":"Flat","dateString":"2020-05-19T21:28:46.926Z","type":"sgv","utcOffset":0},{"_id":"5ec44e638b6aca48aa9b6800","date":1589923427346,"sgv":79,"delta":0,"sysTime":"2020-05-19T21:23:47.637Z","device":"Tomato","direction":"Flat","dateString":"2020-05-19T21:23:47.637Z","type":"sgv","utcOffset":0},{"_id":"5ec44d378b6aca48aa9b5a1a","date":1589923126390,"sgv":81,"delta":0,"sysTime":"2020-05-19T21:18:46.959Z","device":"Tomato","direction":"Flat","dateString":"2020-05-19T21:18:46.959Z","type":"sgv","utcOffset":0},{"_id":"5ec44c0b8b6aca48aa9b4c97","date":1589922826358,"sgv":81,"delta":0,"sysTime":"2020-05-19T21:13:46.934Z","device":"Tomato","direction":"FortyFiveDown","dateString":"2020-05-19T21:13:46.934Z","type":"sgv","utcOffset":0},{"_id":"5ec44adf8b6aca48aa9b3ec7","date":1589922526755,"sgv":93,"delta":0,"sysTime":"2020-05-19T21:08:47.319Z","device":"Tomato","direction":"Flat","dateString":"2020-05-19T21:08:47.319Z","type":"sgv","utcOffset":0},{"_id":"5ec449b38b6aca48aa9b30d6","date":1589922227027,"sgv":93,"delta":0,"sysTime":"2020-05-19T21:03:47.347Z","device":"Tomato","direction":"Flat","dateString":"2020-05-19T21:03:47.347Z","type":"sgv","utcOffset":0},{"_id":"5ec448878b6aca48aa9b2286","date":1589921926683,"sgv":97,"delta":0,"sysTime":"2020-05-19T20:58:46.992Z","device":"Tomato","direction":"Flat","dateString":"2020-05-19T20:58:46.992Z","type":"sgv","utcOffset":0},{"_id":"5ec4475a8b6aca48aa9b1442","date":1589921626205,"sgv":97,"delta":0,"sysTime":"2020-05-19T20:53:46.775Z","device":"Tomato","direction":"Flat","dateString":"2020-05-19T20:53:46.775Z","type":"sgv","utcOffset":0},{"_id":"5ec4462e8b6aca48aa9b0658","date":1589921326271,"sgv":102,"delta":0,"sysTime":"2020-05-19T20:48:46.575Z","device":"Tomato","direction":"Flat","dateString":"2020-05-19T20:48:46.575Z","type":"sgv","utcOffset":0},{"_id":"5ec445038b6aca48aa9af8b3","date":1589921026644,"sgv":109,"delta":0,"sysTime":"2020-05-19T20:43:46.952Z","device":"Tomato","direction":"Flat","dateString":"2020-05-19T20:43:46.952Z","type":"sgv","utcOffset":0},{"_id":"5ec443d78b6aca48aa9aead4","date":1589920726404,"sgv":111,"delta":0,"sysTime":"2020-05-19T20:38:46.991Z","device":"Tomato","direction":"Flat","dateString":"2020-05-19T20:38:46.991Z","type":"sgv","utcOffset":0},{"_id":"5ec442aa8b6aca48aa9adcdb","date":1589920426472,"sgv":113,"delta":0,"sysTime":"2020-05-19T20:33:46.799Z","device":"Tomato","direction":"Flat","dateString":"2020-05-19T20:33:46.799Z","type":"sgv","utcOffset":0},{"_id":"5ec4417f8b6aca48aa9acef8","date":1589920126324,"sgv":116,"delta":0,"sysTime":"2020-05-19T20:28:47.036Z","device":"Tomato","direction":"Flat","dateString":"2020-05-19T20:28:47.036Z","type":"sgv","utcOffset":0},{"_id":"5ec440538b6aca48aa9ac0c3","date":1589919826497,"sgv":120,"delta":0,"sysTime":"2020-05-19T20:23:47.111Z","device":"Tomato","direction":"Flat","dateString":"2020-05-19T20:23:47.111Z","type":"sgv","utcOffset":0},{"_id":"5ec43f278b6aca48aa9ab233","date":1589919526359,"sgv":123,"delta":0,"sysTime":"2020-05-19T20:18:47.027Z","device":"Tomato","direction":"Flat","dateString":"2020-05-19T20:18:47.027Z","type":"sgv","utcOffset":0},{"_id":"5ec43dfa8b6aca48aa9aa4df","date":1589919226428,"sgv":125,"delta":0,"sysTime":"2020-05-19T20:13:46.745Z","device":"Tomato","direction":"Flat","dateString":"2020-05-19T20:13:46.745Z","type":"sgv","utcOffset":0},{"_id":"5ec43ccf8b6aca48aa9a9769","date":1589918926703,"sgv":129,"delta":0,"sysTime":"2020-05-19T20:08:47.290Z","device":"Tomato","direction":"Flat","dateString":"2020-05-19T20:08:47.290Z","type":"sgv","utcOffset":0},{"_id":"5ec43ba28b6aca48aa9a88cd","date":1589918624355,"sgv":131,"delta":0,"sysTime":"2020-05-19T20:03:44.940Z","device":"Tomato","direction":"Flat","dateString":"2020-05-19T20:03:44.940Z","type":"sgv","utcOffset":0},{"_id":"5ec43ba28b6aca48aa9a88d5","date":1589918503321,"sgv":131,"delta":0,"sysTime":"2020-05-19T20:03:44.947Z","device":"Tomato","direction":"Flat","dateString":"2020-05-19T20:03:44.947Z","type":"sgv","utcOffset":0},{"_id":"5ec43ba28b6aca48aa9a88cf","date":1589918203321,"sgv":131,"delta":0,"sysTime":"2020-05-19T20:03:44.954Z","device":"Tomato","direction":"Flat","dateString":"2020-05-19T20:03:44.954Z","type":"sgv","utcOffset":0},{"_id":"5ec43ba28b6aca48aa9a88d3","date":1589917903321,"sgv":131,"delta":0,"sysTime":"2020-05-19T20:03:44.961Z","device":"Tomato","direction":"Flat","dateString":"2020-05-19T20:03:44.961Z","type":"sgv","utcOffset":0},{"_id":"5ec43ba28b6aca48aa9a88d4","date":1589917603321,"sgv":131,"delta":0,"sysTime":"2020-05-19T20:03:44.967Z","device":"Tomato","direction":"Flat","dateString":"2020-05-19T20:03:44.967Z","type":"sgv","utcOffset":0},{"_id":"5ec43ba28b6aca48aa9a88d6","date":1589917303321,"sgv":131,"delta":0,"sysTime":"2020-05-19T20:03:44.974Z","device":"Tomato","direction":"Flat","dateString":"2020-05-19T20:03:44.974Z","type":"sgv","utcOffset":0},{"_id":"5ec43ba28b6aca48aa9a88d9","date":1589917003321,"sgv":130,"delta":0,"sysTime":"2020-05-19T20:03:44.981Z","device":"Tomato","direction":"Flat","dateString":"2020-05-19T20:03:44.981Z","type":"sgv","utcOffset":0},{"_id":"5ec43ba28b6aca48aa9a88e5","date":1589916703321,"sgv":130,"delta":0,"sysTime":"2020-05-19T20:03:44.987Z","device":"Tomato","direction":"Flat","dateString":"2020-05-19T20:03:44.987Z","type":"sgv","utcOffset":0},{"_id":"5ec43ba28b6aca48aa9a88e2","date":1589916403321,"sgv":131,"delta":0,"sysTime":"2020-05-19T20:03:44.994Z","device":"Tomato","direction":"Flat","dateString":"2020-05-19T20:03:44.994Z","type":"sgv","utcOffset":0},{"_id":"5ec43ba28b6aca48aa9a88e3","date":1589916103321,"sgv":131,"delta":0,"sysTime":"2020-05-19T20:03:45.001Z","device":"Tomato","direction":"Flat","dateString":"2020-05-19T20:03:45.001Z","type":"sgv","utcOffset":0},{"_id":"5ec43ba28b6aca48aa9a88e4","date":1589915803321,"sgv":131,"delta":0,"sysTime":"2020-05-19T20:03:45.011Z","device":"Tomato","direction":"Flat","dateString":"2020-05-19T20:03:45.011Z","type":"sgv","utcOffset":0},{"_id":"5ec43ba28b6aca48aa9a88e8","date":1589915503321,"sgv":131,"delta":0,"sysTime":"2020-05-19T20:03:45.018Z","device":"Tomato","direction":"Flat","dateString":"2020-05-19T20:03:45.018Z","type":"sgv","utcOffset":0},{"_id":"5ec43ba28b6aca48aa9a88ec","date":1589915203321,"sgv":130,"delta":0,"sysTime":"2020-05-19T20:03:45.025Z","device":"Tomato","direction":"Flat","dateString":"2020-05-19T20:03:45.025Z","type":"sgv","utcOffset":0},{"_id":"5ec43ba28b6aca48aa9a88f5","date":1589914903321,"sgv":129,"delta":0,"sysTime":"2020-05-19T20:03:45.031Z","device":"Tomato","direction":"Flat","dateString":"2020-05-19T20:03:45.031Z","type":"sgv","utcOffset":0},{"_id":"5ec43ba28b6aca48aa9a88ee","date":1589914603321,"sgv":129,"delta":0,"sysTime":"2020-05-19T20:03:45.037Z","device":"Tomato","direction":"Flat","dateString":"2020-05-19T20:03:45.037Z","type":"sgv","utcOffset":0},{"_id":"5ec43ba28b6aca48aa9a88f0","date":1589914303321,"sgv":128,"delta":0,"sysTime":"2020-05-19T20:03:45.044Z","device":"Tomato","direction":"Flat","dateString":"2020-05-19T20:03:45.044Z","type":"sgv","utcOffset":0},{"_id":"5ec43ba28b6aca48aa9a88f8","date":1589914003321,"sgv":128,"delta":0,"sysTime":"2020-05-19T20:03:45.050Z","device":"Tomato","direction":"Flat","dateString":"2020-05-19T20:03:45.050Z","type":"sgv","utcOffset":0},{"_id":"5ec43ba28b6aca48aa9a8905","date":1589913703321,"sgv":129,"delta":0,"sysTime":"2020-05-19T20:03:45.057Z","device":"Tomato","direction":"Flat","dateString":"2020-05-19T20:03:45.057Z","type":"sgv","utcOffset":0},{"_id":"5ec43ba28b6aca48aa9a88fe","date":1589913403321,"sgv":129,"delta":0,"sysTime":"2020-05-19T20:03:45.064Z","device":"Tomato","direction":"Flat","dateString":"2020-05-19T20:03:45.064Z","type":"sgv","utcOffset":0},{"_id":"5ec43ba28b6aca48aa9a88fa","date":1589913103321,"sgv":130,"delta":0,"sysTime":"2020-05-19T20:03:45.070Z","device":"Tomato","direction":"Flat","dateString":"2020-05-19T20:03:45.070Z","type":"sgv","utcOffset":0},{"_id":"5ec43ba28b6aca48aa9a8902","date":1589912803321,"sgv":131,"delta":0,"sysTime":"2020-05-19T20:03:45.077Z","device":"Tomato","direction":"Flat","dateString":"2020-05-19T20:03:45.077Z","type":"sgv","utcOffset":0},{"_id":"5ec43ba28b6aca48aa9a890b","date":1589912503321,"sgv":131,"delta":0,"sysTime":"2020-05-19T20:03:45.083Z","device":"Tomato","direction":"Flat","dateString":"2020-05-19T20:03:45.083Z","type":"sgv","utcOffset":0},{"_id":"5ec43ba28b6aca48aa9a890f","date":1589912203321,"sgv":132,"delta":0,"sysTime":"2020-05-19T20:03:45.090Z","device":"Tomato","direction":"Flat","dateString":"2020-05-19T20:03:45.090Z","type":"sgv","utcOffset":0},{"_id":"5ec43ba28b6aca48aa9a8912","date":1589911903321,"sgv":132,"delta":0,"sysTime":"2020-05-19T20:03:45.097Z","device":"Tomato","direction":"Flat","dateString":"2020-05-19T20:03:45.097Z","type":"sgv","utcOffset":0},{"_id":"5ec43ba28b6aca48aa9a8909","date":1589911603321,"sgv":134,"delta":0,"sysTime":"2020-05-19T20:03:45.103Z","device":"Tomato","direction":"Flat","dateString":"2020-05-19T20:03:45.103Z","type":"sgv","utcOffset":0},{"_id":"5ec43ba28b6aca48aa9a890d","date":1589911303321,"sgv":136,"delta":0,"sysTime":"2020-05-19T20:03:45.110Z","device":"Tomato","direction":"Flat","dateString":"2020-05-19T20:03:45.110Z","type":"sgv","utcOffset":0},{"_id":"5ec43ba28b6aca48aa9a8916","date":1589911003321,"sgv":140,"delta":0,"sysTime":"2020-05-19T20:03:45.116Z","device":"Tomato","direction":"Flat","dateString":"2020-05-19T20:03:45.116Z","type":"sgv","utcOffset":0},{"_id":"5ec43ba28b6aca48aa9a891c","date":1589910703321,"sgv":141,"delta":0,"sysTime":"2020-05-19T20:03:45.123Z","device":"Tomato","direction":"Flat","dateString":"2020-05-19T20:03:45.123Z","type":"sgv","utcOffset":0},{"_id":"5ec43ba28b6aca48aa9a8919","date":1589910403321,"sgv":143,"delta":0,"sysTime":"2020-05-19T20:03:45.129Z","device":"Tomato","direction":"Flat","dateString":"2020-05-19T20:03:45.129Z","type":"sgv","utcOffset":0},{"_id":"5ec43ba28b6aca48aa9a8926","date":1589910103321,"sgv":145,"delta":0,"sysTime":"2020-05-19T20:03:45.136Z","device":"Tomato","direction":"Flat","dateString":"2020-05-19T20:03:45.136Z","type":"sgv","utcOffset":0},{"_id":"5ec43ba28b6aca48aa9a891e","date":1589909803321,"sgv":145,"delta":0,"sysTime":"2020-05-19T20:03:45.143Z","device":"Tomato","direction":"Flat","dateString":"2020-05-19T20:03:45.143Z","type":"sgv","utcOffset":0},{"_id":"5ec43ba28b6aca48aa9a8928","date":1589909503321,"sgv":145,"delta":0,"sysTime":"2020-05-19T20:03:45.150Z","device":"Tomato","direction":"Flat","dateString":"2020-05-19T20:03:45.150Z","type":"sgv","utcOffset":0},{"_id":"5ec43ba28b6aca48aa9a892a","date":1589909203321,"sgv":145,"delta":0,"sysTime":"2020-05-19T20:03:45.157Z","device":"Tomato","direction":"Flat","dateString":"2020-05-19T20:03:45.157Z","type":"sgv","utcOffset":0},{"_id":"5ec43ba28b6aca48aa9a8927","date":1589908903321,"sgv":144,"delta":0,"sysTime":"2020-05-19T20:03:45.164Z","device":"Tomato","direction":"Flat","dateString":"2020-05-19T20:03:45.164Z","type":"sgv","utcOffset":0},{"_id":"5ec43ba28b6aca48aa9a8931","date":1589908603321,"sgv":144,"delta":0,"sysTime":"2020-05-19T20:03:45.170Z","device":"Tomato","direction":"Flat","dateString":"2020-05-19T20:03:45.170Z","type":"sgv","utcOffset":0},{"_id":"5ec43ba28b6aca48aa9a8938","date":1589908303321,"sgv":145,"delta":0,"sysTime":"2020-05-19T20:03:45.177Z","device":"Tomato","direction":"Flat","dateString":"2020-05-19T20:03:45.177Z","type":"sgv","utcOffset":0},{"_id":"5ec43ba28b6aca48aa9a8933","date":1589908003321,"sgv":146,"delta":0,"sysTime":"2020-05-19T20:03:45.183Z","device":"Tomato","direction":"Flat","dateString":"2020-05-19T20:03:45.183Z","type":"sgv","utcOffset":0},{"_id":"5ec43ba28b6aca48aa9a893c","date":1589907703321,"sgv":148,"delta":0,"sysTime":"2020-05-19T20:03:45.190Z","device":"Tomato","direction":"Flat","dateString":"2020-05-19T20:03:45.190Z","type":"sgv","utcOffset":0},{"_id":"5ec43ba28b6aca48aa9a8935","date":1589907403321,"sgv":150,"delta":0,"sysTime":"2020-05-19T20:03:45.197Z","device":"Tomato","direction":"Flat","dateString":"2020-05-19T20:03:45.197Z","type":"sgv","utcOffset":0},{"_id":"5ec43ba28b6aca48aa9a8944","date":1589907103321,"sgv":153,"delta":0,"sysTime":"2020-05-19T20:03:45.203Z","device":"Tomato","direction":"Flat","dateString":"2020-05-19T20:03:45.203Z","type":"sgv","utcOffset":0},{"_id":"5ec43ba28b6aca48aa9a894d","date":1589906803321,"sgv":158,"delta":0,"sysTime":"2020-05-19T20:03:45.210Z","device":"Tomato","direction":"Flat","dateString":"2020-05-19T20:03:45.210Z","type":"sgv","utcOffset":0},{"_id":"5ec43ba28b6aca48aa9a894a","date":1589906503321,"sgv":161,"delta":0,"sysTime":"2020-05-19T20:03:45.216Z","device":"Tomato","direction":"Flat","dateString":"2020-05-19T20:03:45.216Z","type":"sgv","utcOffset":0},{"_id":"5ec43ba28b6aca48aa9a894f","date":1589906203321,"sgv":164,"delta":0,"sysTime":"2020-05-19T20:03:45.223Z","device":"Tomato","direction":"Flat","dateString":"2020-05-19T20:03:45.223Z","type":"sgv","utcOffset":0},{"_id":"5ec43ba28b6aca48aa9a8947","date":1589905903321,"sgv":168,"delta":0,"sysTime":"2020-05-19T20:03:45.230Z","device":"Tomato","direction":"Flat","dateString":"2020-05-19T20:03:45.230Z","type":"sgv","utcOffset":0},{"_id":"5ec43ba28b6aca48aa9a8952","date":1589905603321,"sgv":170,"delta":0,"sysTime":"2020-05-19T20:03:45.236Z","device":"Tomato","direction":"Flat","dateString":"2020-05-19T20:03:45.236Z","type":"sgv","utcOffset":0},{"_id":"5ec43ba28b6aca48aa9a8960","date":1589905303321,"sgv":173,"delta":0,"sysTime":"2020-05-19T20:03:45.243Z","device":"Tomato","direction":"Flat","dateString":"2020-05-19T20:03:45.243Z","type":"sgv","utcOffset":0},{"_id":"5ec43ba28b6aca48aa9a8956","date":1589905003321,"sgv":175,"delta":0,"sysTime":"2020-05-19T20:03:45.250Z","device":"Tomato","direction":"Flat","dateString":"2020-05-19T20:03:45.250Z","type":"sgv","utcOffset":0},{"_id":"5ec43ba28b6aca48aa9a8962","date":1589904703321,"sgv":177,"delta":0,"sysTime":"2020-05-19T20:03:45.257Z","device":"Tomato","direction":"Flat","dateString":"2020-05-19T20:03:45.257Z","type":"sgv","utcOffset":0},{"_id":"5ec43ba28b6aca48aa9a8955","date":1589904403321,"sgv":179,"delta":0,"sysTime":"2020-05-19T20:03:45.264Z","device":"Tomato","direction":"Flat","dateString":"2020-05-19T20:03:45.264Z","type":"sgv","utcOffset":0},{"_id":"5ec43ba28b6aca48aa9a8963","date":1589904103321,"sgv":180,"delta":0,"sysTime":"2020-05-19T20:03:45.270Z","device":"Tomato","direction":"Flat","dateString":"2020-05-19T20:03:45.270Z","type":"sgv","utcOffset":0},{"_id":"5ec43ba28b6aca48aa9a896a","date":1589903803321,"sgv":181,"delta":0,"sysTime":"2020-05-19T20:03:45.277Z","device":"Tomato","direction":"Flat","dateString":"2020-05-19T20:03:45.277Z","type":"sgv","utcOffset":0},{"_id":"5ec43ba28b6aca48aa9a8969","date":1589903503321,"sgv":181,"delta":0,"sysTime":"2020-05-19T20:03:45.284Z","device":"Tomato","direction":"Flat","dateString":"2020-05-19T20:03:45.284Z","type":"sgv","utcOffset":0},{"_id":"5ec43ba28b6aca48aa9a896b","date":1589903203321,"sgv":181,"delta":0,"sysTime":"2020-05-19T20:03:45.290Z","device":"Tomato","direction":"Flat","dateString":"2020-05-19T20:03:45.290Z","type":"sgv","utcOffset":0},{"_id":"5ec43ba28b6aca48aa9a8968","date":1589902903321,"sgv":182,"delta":0,"sysTime":"2020-05-19T20:03:45.297Z","device":"Tomato","direction":"Flat","dateString":"2020-05-19T20:03:45.297Z","type":"sgv","utcOffset":0},{"_id":"5ec43ba38b6aca48aa9a896d","date":1589902603321,"sgv":183,"delta":0,"sysTime":"2020-05-19T20:03:45.303Z","device":"Tomato","direction":"Flat","dateString":"2020-05-19T20:03:45.303Z","type":"sgv","utcOffset":0},{"_id":"5ec43ba38b6aca48aa9a8975","date":1589902303321,"sgv":184,"delta":0,"sysTime":"2020-05-19T20:03:45.310Z","device":"Tomato","direction":"Flat","dateString":"2020-05-19T20:03:45.310Z","type":"sgv","utcOffset":0},{"_id":"5ec43ba38b6aca48aa9a8974","date":1589902003321,"sgv":184,"delta":0,"sysTime":"2020-05-19T20:03:45.317Z","device":"Tomato","direction":"Flat","dateString":"2020-05-19T20:03:45.317Z","type":"sgv","utcOffset":0},{"_id":"5ec43ba38b6aca48aa9a897a","date":1589901703321,"sgv":183,"delta":0,"sysTime":"2020-05-19T20:03:45.326Z","device":"Tomato","direction":"Flat","dateString":"2020-05-19T20:03:45.326Z","type":"sgv","utcOffset":0},{"_id":"5ec43ba38b6aca48aa9a8977","date":1589901403321,"sgv":182,"delta":0,"sysTime":"2020-05-19T20:03:45.333Z","device":"Tomato","direction":"Flat","dateString":"2020-05-19T20:03:45.333Z","type":"sgv","utcOffset":0},{"_id":"5ec43ba38b6aca48aa9a898d","date":1589901103321,"sgv":182,"delta":0,"sysTime":"2020-05-19T20:03:45.340Z","device":"Tomato","direction":"Flat","dateString":"2020-05-19T20:03:45.340Z","type":"sgv","utcOffset":0},{"_id":"5ec43ba38b6aca48aa9a898e","date":1589900803321,"sgv":181,"delta":0,"sysTime":"2020-05-19T20:03:45.346Z","device":"Tomato","direction":"Flat","dateString":"2020-05-19T20:03:45.346Z","type":"sgv","utcOffset":0},{"_id":"5ec43ba38b6aca48aa9a8980","date":1589900503321,"sgv":182,"delta":0,"sysTime":"2020-05-19T20:03:45.353Z","device":"Tomato","direction":"Flat","dateString":"2020-05-19T20:03:45.353Z","type":"sgv","utcOffset":0},{"_id":"5ec43ba38b6aca48aa9a897d","date":1589900203321,"sgv":182,"delta":0,"sysTime":"2020-05-19T20:03:45.360Z","device":"Tomato","direction":"Flat","dateString":"2020-05-19T20:03:45.360Z","type":"sgv","utcOffset":0},{"_id":"5ec43ba38b6aca48aa9a8984","date":1589899903321,"sgv":185,"delta":0,"sysTime":"2020-05-19T20:03:45.366Z","device":"Tomato","direction":"Flat","dateString":"2020-05-19T20:03:45.366Z","type":"sgv","utcOffset":0},{"_id":"5ec43ba38b6aca48aa9a899d","date":1589899603321,"sgv":189,"delta":0,"sysTime":"2020-05-19T20:03:45.373Z","device":"Tomato","direction":"Flat","dateString":"2020-05-19T20:03:45.373Z","type":"sgv","utcOffset":0},{"_id":"5ec43ba38b6aca48aa9a899f","date":1589899303321,"sgv":191,"delta":0,"sysTime":"2020-05-19T20:03:45.380Z","device":"Tomato","direction":"Flat","dateString":"2020-05-19T20:03:45.380Z","type":"sgv","utcOffset":0},{"_id":"5ec43ba38b6aca48aa9a898f","date":1589899003321,"sgv":192,"delta":0,"sysTime":"2020-05-19T20:03:45.386Z","device":"Tomato","direction":"Flat","dateString":"2020-05-19T20:03:45.386Z","type":"sgv","utcOffset":0},{"_id":"5ec43ba38b6aca48aa9a8990","date":1589898703321,"sgv":192,"delta":0,"sysTime":"2020-05-19T20:03:45.393Z","device":"Tomato","direction":"Flat","dateString":"2020-05-19T20:03:45.393Z","type":"sgv","utcOffset":0},{"_id":"5ec43ba38b6aca48aa9a8995","date":1589898403321,"sgv":193,"delta":0,"sysTime":"2020-05-19T20:03:45.400Z","device":"Tomato","direction":"Flat","dateString":"2020-05-19T20:03:45.400Z","type":"sgv","utcOffset":0},{"_id":"5ec43ba38b6aca48aa9a89a8","date":1589898103321,"sgv":193,"delta":0,"sysTime":"2020-05-19T20:03:45.407Z","device":"Tomato","direction":"Flat","dateString":"2020-05-19T20:03:45.407Z","type":"sgv","utcOffset":0},{"_id":"5ec43ba38b6aca48aa9a89b3","date":1589897803321,"sgv":192,"delta":0,"sysTime":"2020-05-19T20:03:45.413Z","device":"Tomato","direction":"Flat","dateString":"2020-05-19T20:03:45.413Z","type":"sgv","utcOffset":0},{"_id":"5ec43ba38b6aca48aa9a89a0","date":1589897503321,"sgv":193,"delta":0,"sysTime":"2020-05-19T20:03:45.420Z","device":"Tomato","direction":"Flat","dateString":"2020-05-19T20:03:45.420Z","type":"sgv","utcOffset":0},{"_id":"5ec43ba38b6aca48aa9a899e","date":1589897203321,"sgv":196,"delta":0,"sysTime":"2020-05-19T20:03:45.427Z","device":"Tomato","direction":"Flat","dateString":"2020-05-19T20:03:45.427Z","type":"sgv","utcOffset":0},{"_id":"5ec43ba38b6aca48aa9a89a2","date":1589896903321,"sgv":199,"delta":0,"sysTime":"2020-05-19T20:03:45.433Z","device":"Tomato","direction":"Flat","dateString":"2020-05-19T20:03:45.433Z","type":"sgv","utcOffset":0},{"_id":"5ec43ba38b6aca48aa9a89b4","date":1589896603321,"sgv":204,"delta":0,"sysTime":"2020-05-19T20:03:45.440Z","device":"Tomato","direction":"Flat","dateString":"2020-05-19T20:03:45.440Z","type":"sgv","utcOffset":0},{"_id":"5ec43ba38b6aca48aa9a89b8","date":1589896303321,"sgv":205,"delta":0,"sysTime":"2020-05-19T20:03:45.447Z","device":"Tomato","direction":"Flat","dateString":"2020-05-19T20:03:45.447Z","type":"sgv","utcOffset":0},{"_id":"5ec43ba38b6aca48aa9a89ac","date":1589896003321,"sgv":206,"delta":0,"sysTime":"2020-05-19T20:03:45.454Z","device":"Tomato","direction":"Flat","dateString":"2020-05-19T20:03:45.454Z","type":"sgv","utcOffset":0},{"_id":"5ec43ba38b6aca48aa9a89b2","date":1589895703321,"sgv":207,"delta":0,"sysTime":"2020-05-19T20:03:45.461Z","device":"Tomato","direction":"Flat","dateString":"2020-05-19T20:03:45.461Z","type":"sgv","utcOffset":0},{"_id":"5ec43ba38b6aca48aa9a89b1","date":1589895403321,"sgv":211,"delta":0,"sysTime":"2020-05-19T20:03:45.468Z","device":"Tomato","direction":"Flat","dateString":"2020-05-19T20:03:45.468Z","type":"sgv","utcOffset":0},{"_id":"5ec43ba38b6aca48aa9a89bb","date":1589895103321,"sgv":214,"delta":0,"sysTime":"2020-05-19T20:03:45.477Z","device":"Tomato","direction":"Flat","dateString":"2020-05-19T20:03:45.477Z","type":"sgv","utcOffset":0},{"_id":"5ec43ba38b6aca48aa9a89bd","date":1589894803321,"sgv":218,"delta":0,"sysTime":"2020-05-19T20:03:45.485Z","device":"Tomato","direction":"Flat","dateString":"2020-05-19T20:03:45.485Z","type":"sgv","utcOffset":0},{"_id":"5ec3dd1f8b6aca48aa9616c3","date":1589894430391,"sgv":234,"delta":0,"sysTime":"2020-05-19T13:20:30.987Z","device":"Tomato","direction":"Flat","dateString":"2020-05-19T13:20:30.987Z","type":"sgv","utcOffset":0},{"_id":"5ec3dd1f8b6aca48aa9616c5","date":1589894365604,"sgv":233,"delta":0,"sysTime":"2020-05-19T13:20:30.997Z","device":"Tomato","direction":"Flat","dateString":"2020-05-19T13:20:30.997Z","type":"sgv","utcOffset":0},{"_id":"5ec3dd1f8b6aca48aa9616c7","date":1589894065604,"sgv":232,"delta":0,"sysTime":"2020-05-19T13:20:31.010Z","device":"Tomato","direction":"Flat","dateString":"2020-05-19T13:20:31.010Z","type":"sgv","utcOffset":0},{"_id":"5ec3dabe8b6aca48aa95fa40","date":1589893821928,"sgv":231,"delta":0,"sysTime":"2020-05-19T13:10:22.510Z","device":"Tomato","direction":"Flat","dateString":"2020-05-19T13:10:22.510Z","type":"sgv","utcOffset":0},{"_id":"5ec3dabe8b6aca48aa95fa45","date":1589893756166,"sgv":231,"delta":0,"sysTime":"2020-05-19T13:10:22.517Z","device":"Tomato","direction":"Flat","dateString":"2020-05-19T13:10:22.517Z","type":"sgv","utcOffset":0},{"_id":"5ec3dabe8b6aca48aa95fa43","date":1589893456166,"sgv":228,"delta":0,"sysTime":"2020-05-19T13:10:22.523Z","device":"Tomato","direction":"Flat","dateString":"2020-05-19T13:10:22.523Z","type":"sgv","utcOffset":0},{"_id":"5ec3d85c8b6aca48aa95dd3d","date":1589893211892,"sgv":225,"delta":0,"sysTime":"2020-05-19T13:00:12.494Z","device":"Tomato","direction":"Flat","dateString":"2020-05-19T13:00:12.494Z","type":"sgv","utcOffset":0},{"_id":"5ec3d85c8b6aca48aa95dd40","date":1589893154375,"sgv":224,"delta":0,"sysTime":"2020-05-19T13:00:12.500Z","device":"Tomato","direction":"Flat","dateString":"2020-05-19T13:00:12.500Z","type":"sgv","utcOffset":0},{"_id":"5ec3d85c8b6aca48aa95dd3e","date":1589892854375,"sgv":222,"delta":0,"sysTime":"2020-05-19T13:00:12.507Z","device":"Tomato","direction":"Flat","dateString":"2020-05-19T13:00:12.507Z","type":"sgv","utcOffset":0},{"_id":"5ec3d85c8b6aca48aa95dd3f","date":1589892554375,"sgv":220,"delta":0,"sysTime":"2020-05-19T13:00:12.514Z","device":"Tomato","direction":"Flat","dateString":"2020-05-19T13:00:12.514Z","type":"sgv","utcOffset":0},{"_id":"5ec3d4cf8b6aca48aa95b39d","date":1589892303224,"sgv":215,"delta":0,"sysTime":"2020-05-19T12:45:03.528Z","device":"Tomato","direction":"Flat","dateString":"2020-05-19T12:45:03.528Z","type":"sgv","utcOffset":0},{"_id":"5ec3d3a38b6aca48aa95a5fd","date":1589892003182,"sgv":212,"delta":0,"sysTime":"2020-05-19T12:40:03.659Z","device":"Tomato","direction":"Flat","dateString":"2020-05-19T12:40:03.659Z","type":"sgv","utcOffset":0}]